README.md
setup.py
bidon/__init__.py
bidon/configuration.py
bidon/data_table.py
bidon/field_mapping.py
bidon/json_patch.py
bidon.egg-info/PKG-INFO
bidon.egg-info/SOURCES.txt
bidon.egg-info/dependency_links.txt
bidon.egg-info/top_level.txt
bidon/db/__init__.py
bidon/db/access/__init__.py
bidon/db/access/data_access.py
bidon/db/access/model_access.py
bidon/db/access/pg_advisory_lock.py
bidon/db/core/__init__.py
bidon/db/core/data_access_core.py
bidon/db/core/sql_writer.py
bidon/db/model/__init__.py
bidon/db/model/foreign_model_wrapper.py
bidon/db/model/model_base.py
bidon/db/model/validation.py
bidon/experimental/__init__.py
bidon/experimental/finite_state_machine.py
bidon/experimental/transfer_tracker.py
bidon/spreadsheet/__init__.py
bidon/spreadsheet/base.py
bidon/spreadsheet/csv.py
bidon/spreadsheet/excel.py
bidon/spreadsheet/open_document.py
bidon/util/__init__.py
bidon/util/convert.py
bidon/util/date.py
bidon/util/terminal.py
bidon/util/transform.py
bidon/xml/__init__.py
bidon/xml/stream_writer.py