Metadata-Version: 1.1
Name: bidon
Version: 1.0.7
Summary: A simple, easy to use, and flexible data handling library
Home-page: https://github.com/treycucco/bidon
Author: Trey Cucco
Author-email: fcucco@gmail.com
License: MIT
Download-URL: https://github.com/treycucco/bidon/tarball/master
Platform: any
Classifier: Development Status :: 4 - Beta
Classifier: Intended Audience :: Developers
Classifier: License :: OSI Approved :: MIT License
Classifier: Natural Language :: English
Classifier: Operating System :: OS Independent
Classifier: Programming Language :: Python
Classifier: Programming Language :: Python :: 3
Classifier: Programming Language :: Python :: 3.4
Classifier: Programming Language :: Python :: 3 :: Only
